[
  {
    "id": 1,
    "title": "Travel Tips for Solo Travelers",
    "summary": "Essential tips for solo travelers.",
    "content": "Yalnız seyahat etmek, bana her zaman özgürlük ve keşif hissi verir. Solo seyahatlerimde, kendimi daha iyi tanıma fırsatı buluyorum ve dünyayı kendi gözlerimle keşfetmenin tadını çıkarıyorum. Yalnız seyahatin en önemli ipuçlarından biri, güvenliğinizi ön planda tutmaktır. Seyahat öncesi gideceğiniz yer hakkında detaylı araştırma yapmak ve güvenli bölgelerde konaklamak önemlidir. Ayrıca, seyahat planlarınızı sevdiklerinizle paylaşmak ve acil durumlar için bir iletişim planı oluşturmak da gereklidir. Seyahatiniz sırasında, yerel halkla iletişim kurmaktan çekinmeyin. Bu, hem güvenliğinizi artırır hem de yeni arkadaşlıklar kurmanıza yardımcı olur. Hafif ve pratik bir bavul hazırlamak, seyahatinizin daha konforlu geçmesini sağlar. En önemlisi, anın tadını çıkarın ve her yeni deneyimin size kattığı değerlerin farkında olun. Solo seyahat etmek, dünyayı keşfetmenin en özgün yollarından biridir.",
    "author": "Orhan Yardım",
    "date": "05 Ocak 2025",
    "image": "/images/travel_destinations2.jpg"
  },
  {
    "id": 2,
    "title": "Top 10 Travel Destinations for 2025",
    "summary": "Explore the best travel destinations to visit in 2025.",
    "content": "2025 yılında gezginlerin mutlaka görmesi gereken yerler arasında çeşitli destinasyonlar bulunuyor. Bu yazıda, 2025'in en popüler seyahat noktalarını keşfedeceksiniz.\n\n1. Tokyo, Japonya: Tokyo, modern teknoloji ve geleneksel Japon kültürünün mükemmel bir karışımını sunar. Şehirde, tarihi tapınaklar ve gökdelenler yan yana bulunur. Ayrıca, ünlü Japon mutfağının tadını çıkarabilirsiniz.\n\n2. Cape Town, Güney Afrika: Doğal güzellikleri ve zengin kültürel mirası ile Cape Town, macera severler için mükemmel bir destinasyondur. Masa Dağı'na tırmanabilir ve ünlü Kirstenbosch Botanik Bahçesi'ni ziyaret edebilirsiniz.\n\n3. Barcelona, İspanya: Barcelona, dünyaca ünlü mimar Antoni Gaudí'nin eserleri ile ünlüdür. Sagrada Família ve Park Güell gibi ikonik yapıları görmeli ve Akdeniz'in güzel plajlarında dinlenmelisiniz.\n\n4. Reykjavik, İzlanda: İzlanda'nın başkenti Reykjavik, doğa severler için bir cennettir. Kuzey Işıkları'nı izleyebilir ve ülkenin benzersiz coğrafyasını keşfedebilirsiniz.\n\n5. Sydney, Avustralya: Sydney, güzel plajları ve dünyaca ünlü Sydney Opera Evi ile tanınır. Şehirde ayrıca çeşitli su sporları yapabilirsiniz.\n\n6. Santorini, Yunanistan: Beyaz badanalı evleri ve mavi çatılı kiliseleri ile ünlü Santorini, romantik bir tatil için mükemmel bir yerdir. Adada güneşin batışını izlemek unutulmaz bir deneyim sunar.\n\n7. New York City, ABD: New York City, dünyanın en ünlü şehirlerinden biridir. Central Park, Times Square ve Empire State Building gibi ikonik yerleri ziyaret etmelisiniz.\n\n8. Rio de Janeiro, Brezilya: Rio de Janeiro, plajları, Samba müziği ve Karnavalı ile ünlüdür. Şehirde ayrıca ünlü Kurtarıcı İsa Heykeli'ni de görebilirsiniz.\n\n9. Paris, Fransa: Paris, aşkın ve sanatın şehri olarak bilinir. Eyfel Kulesi, Louvre Müzesi ve Notre-Dame Katedrali gibi yerleri mutlaka ziyaret etmelisiniz.\n\n10. Bali, Endonezya: Bali, tropikal cenneti ve huzurlu atmosferi ile tanınır. Adada yoga yapabilir ve Bali'nin güzel plajlarında dinlenebilirsiniz.\n\nBu destinasyonlar, 2025 yılında unutulmaz bir seyahat deneyimi yaşamanız için harika seçenekler sunar. Yeni yerler keşfetmek ve farklı kültürlerle tanışmak için bu yerleri listenize ekleyin.",
    "author": "Gezgin Mehmet",
    "date": "2 Ocak 2025",
    "image": "/images/travel_destinations.jpg"
  }  
]



